luci_cli_bin/_internal/_asyncio.pyd
luci_cli_bin/_internal/_bz2.pyd
luci_cli_bin/_internal/_cffi_backend.cp310-win_amd64.pyd
luci_cli_bin/_internal/_ctypes.pyd
luci_cli_bin/_internal/_decimal.pyd
luci_cli_bin/_internal/_elementtree.pyd
luci_cli_bin/_internal/_hashlib.pyd
luci_cli_bin/_internal/_lzma.pyd
luci_cli_bin/_internal/_multiprocessing.pyd
luci_cli_bin/_internal/_overlapped.pyd
luci_cli_bin/_internal/_queue.pyd
luci_cli_bin/_internal/_socket.pyd
luci_cli_bin/_internal/_ssl.pyd
luci_cli_bin/_internal/_uuid.pyd
luci_cli_bin/_internal/api-ms-win-core-console-l1-1-0.dll
luci_cli_bin/_internal/api-ms-win-core-datetime-l1-1-0.dll
luci_cli_bin/_internal/api-ms-win-core-debug-l1-1-0.dll
luci_cli_bin/_internal/api-ms-win-core-errorhandling-l1-1-0.dll
luci_cli_bin/_internal/api-ms-win-core-file-l1-1-0.dll
luci_cli_bin/_internal/api-ms-win-core-file-l1-2-0.dll
luci_cli_bin/_internal/api-ms-win-core-file-l2-1-0.dll
luci_cli_bin/_internal/api-ms-win-core-handle-l1-1-0.dll
luci_cli_bin/_internal/api-ms-win-core-heap-l1-1-0.dll
luci_cli_bin/_internal/api-ms-win-core-interlocked-l1-1-0.dll
luci_cli_bin/_internal/api-ms-win-core-libraryloader-l1-1-0.dll
luci_cli_bin/_internal/api-ms-win-core-localization-l1-2-0.dll
luci_cli_bin/_internal/api-ms-win-core-memory-l1-1-0.dll
luci_cli_bin/_internal/api-ms-win-core-namedpipe-l1-1-0.dll
luci_cli_bin/_internal/api-ms-win-core-processenvironment-l1-1-0.dll
luci_cli_bin/_internal/api-ms-win-core-processthreads-l1-1-0.dll
luci_cli_bin/_internal/api-ms-win-core-processthreads-l1-1-1.dll
luci_cli_bin/_internal/api-ms-win-core-profile-l1-1-0.dll
luci_cli_bin/_internal/api-ms-win-core-rtlsupport-l1-1-0.dll
luci_cli_bin/_internal/api-ms-win-core-string-l1-1-0.dll
luci_cli_bin/_internal/api-ms-win-core-synch-l1-1-0.dll
luci_cli_bin/_internal/api-ms-win-core-synch-l1-2-0.dll
luci_cli_bin/_internal/api-ms-win-core-sysinfo-l1-1-0.dll
luci_cli_bin/_internal/api-ms-win-core-timezone-l1-1-0.dll
luci_cli_bin/_internal/cryptography-41.0.7.dist-info/INSTALLER
luci_cli_bin/_internal/cryptography-41.0.7.dist-info/LICENSE
luci_cli_bin/_internal/cryptography-41.0.7.dist-info/LICENSE.APACHE
luci_cli_bin/_internal/cryptography-41.0.7.dist-info/LICENSE.BSD
luci_cli_bin/_internal/cryptography-41.0.7.dist-info/METADATA
luci_cli_bin/_internal/cryptography-41.0.7.dist-info/RECORD
luci_cli_bin/_internal/cryptography-41.0.7.dist-info/top_level.txt
luci_cli_bin/_internal/cryptography-41.0.7.dist-info/WHEEL
luci_cli_bin/_internal/importlib_metadata-7.0.1.dist-info/INSTALLER
luci_cli_bin/_internal/importlib_metadata-7.0.1.dist-info/LICENSE
luci_cli_bin/_internal/importlib_metadata-7.0.1.dist-info/METADATA
luci_cli_bin/_internal/importlib_metadata-7.0.1.dist-info/RECORD
luci_cli_bin/_internal/importlib_metadata-7.0.1.dist-info/top_level.txt
luci_cli_bin/_internal/importlib_metadata-7.0.1.dist-info/WHEEL
luci_cli_bin/_internal/keyring-23.13.1.dist-info/entry_points.txt
luci_cli_bin/_internal/keyring-23.13.1.dist-info/INSTALLER
luci_cli_bin/_internal/keyring-23.13.1.dist-info/LICENSE
luci_cli_bin/_internal/keyring-23.13.1.dist-info/METADATA
luci_cli_bin/_internal/keyring-23.13.1.dist-info/RECORD
luci_cli_bin/_internal/keyring-23.13.1.dist-info/top_level.txt
luci_cli_bin/_internal/keyring-23.13.1.dist-info/WHEEL
luci_cli_bin/_internal/luci_cli-0.3.0.dist-info/direct_url.json
luci_cli_bin/_internal/luci_cli-0.3.0.dist-info/entry_points.txt
luci_cli_bin/_internal/luci_cli-0.3.0.dist-info/INSTALLER
luci_cli_bin/_internal/luci_cli-0.3.0.dist-info/METADATA
luci_cli_bin/_internal/luci_cli-0.3.0.dist-info/RECORD
luci_cli_bin/_internal/wheel-0.42.0.dist-info/entry_points.txt
luci_cli_bin/_internal/wheel-0.42.0.dist-info/INSTALLER
luci_cli_bin/_internal/wheel-0.42.0.dist-info/LICENSE.txt
luci_cli_bin/_internal/wheel-0.42.0.dist-info/METADATA
luci_cli_bin/_internal/wheel-0.42.0.dist-info/RECORD
luci_cli_bin/_internal/wheel-0.42.0.dist-info/WHEEL
luci_cli_bin-0.3.0.dist-info/entry_points.txt
luci_cli_bin-0.3.0.dist-info/METADATA
luci_cli_bin-0.3.0.dist-info/WHEEL
luci_cli_bin-0.3.0.dist-info/RECORD
